README.md
setup.py
anndataks/__init__.py
anndataks/_version.py
anndataks/adata.py
anndataks/config.py
anndataks/stats.py
anndataks.egg-info/PKG-INFO
anndataks.egg-info/SOURCES.txt
anndataks.egg-info/dependency_links.txt
anndataks.egg-info/requires.txt
anndataks.egg-info/top_level.txt
test/test_small.py