Metadata-Version: 1.2
Name: anndataks
Version: 0.1.3
Summary: KS test for single cell RNA Seq AnnData
Home-page: https://github.com/iosonofabio/anndata_kolmogorov_smirnov
Author: Fabio Zanini
Author-email: fabio.zanini@unsw.edu.au
Maintainer: Fabio Zanini
Maintainer-email: fabio.zanini@unsw.edu.au
License: GPL3
Platform: UNKNOWN
Classifier: Development Status :: 3 - Alpha
Classifier: Topic :: Scientific/Engineering :: Bio-Informatics
Classifier: Intended Audience :: Developers
Classifier: Intended Audience :: Science/Research
Classifier: License :: OSI Approved :: GNU General Public License (GPL)
Classifier: Operating System :: POSIX
Classifier: Programming Language :: Python
